01_verilog/counter.v
`timescale 1ns/1ps

module counter(
     clk,
     reset
);

input clk;
input reset;

reg [15 : 0] cnt;

always@(posedge clk or negedge reset) begin
    if(!reset) begin
        cnt <= 16'd0;
    end
    else begin
        cnt <= cnt + 16'd1;
    end
end

endmodule

01_verilog/tb.v
`timescale 1ns/1ps

module tb();

reg clk;
reg reset;

counter cnt(
    .clk(clk),
    .reset(reset)
);

initial begin
    clk = 1'b0;
    reset = 1'b0;

    #100
    reset = 1'b1;
end
initial begin
	$dumpfile("test_out.vcd");
	$dumpvars;
	#1000
	$finish;

end

always #5 clk <= ~clk;

endmodule

01_verilog/test_out.vcd
$date
	Sun Jun  6 22:32:16 2021
$end
$version
	Icarus Verilog
$end
$timescale
	1ps
$end
$scope module tb $end
$var reg 1 ! clk $end
$var reg 1 " reset $end
$scope module cnt $end
$var wire 1 ! clk $end
$var wire 1 " reset $end
$var reg 16 # cnt [15:0] $end
$upscope $end
$upscope $end
$enddefinitions $end
#0
$dumpvars
b0 #
0"
0!
$end
#5000
1!
#10000
0!
#15000
1!
#20000
0!
#25000
1!
#30000
0!
#35000
1!
#40000
0!
#45000
1!
#50000
0!
#55000
1!
#60000
0!
#65000
1!
#70000
0!
#75000
1!
#80000
0!
#85000
1!
#90000
0!
#95000
1!
#100000
0!
1"
#105000
b1 #
1!
#110000
0!
#115000
b10 #
1!
#120000
0!
#125000
b11 #
1!
#130000
0!
#135000
b100 #
1!
#140000
0!
#145000
b101 #
1!
#150000
0!
#155000
b110 #
1!
#160000
0!
#165000
b111 #
1!
#170000
0!
#175000
b1000 #
1!
#180000
0!
#185000
b1001 #
1!
#190000
0!
#195000
b1010 #
1!
#200000
0!
#205000
b1011 #
1!
#210000
0!
#215000
b1100 #
1!
#220000
0!
#225000
b1101 #
1!
#230000
0!
#235000
b1110 #
1!
#240000
0!
#245000
b1111 #
1!
#250000
0!
#255000
b10000 #
1!
#260000
0!
#265000
b10001 #
1!
#270000
0!
#275000
b10010 #
1!
#280000
0!
#285000
b10011 #
1!
#290000
0!
#295000
b10100 #
1!
#300000
0!
#305000
b10101 #
1!
#310000
0!
#315000
b10110 #
1!
#320000
0!
#325000
b10111 #
1!
#330000
0!
#335000
b11000 #
1!
#340000
0!
#345000
b11001 #
1!
#350000
0!
#355000
b11010 #
1!
#360000
0!
#365000
b11011 #
1!
#370000
0!
#375000
b11100 #
1!
#380000
0!
#385000
b11101 #
1!
#390000
0!
#395000
b11110 #
1!
#400000
0!
#405000
b11111 #
1!
#410000
0!
#415000
b100000 #
1!
#420000
0!
#425000
b100001 #
1!
#430000
0!
#435000
b100010 #
1!
#440000
0!
#445000
b100011 #
1!
#450000
0!
#455000
b100100 #
1!
#460000
0!
#465000
b100101 #
1!
#470000
0!
#475000
b100110 #
1!
#480000
0!
#485000
b100111 #
1!
#490000
0!
#495000
b101000 #
1!
#500000
0!
#505000
b101001 #
1!
#510000
0!
#515000
b101010 #
1!
#520000
0!
#525000
b101011 #
1!
#530000
0!
#535000
b101100 #
1!
#540000
0!
#545000
b101101 #
1!
#550000
0!
#555000
b101110 #
1!
#560000
0!
#565000
b101111 #
1!
#570000
0!
#575000
b110000 #
1!
#580000
0!
#585000
b110001 #
1!
#590000
0!
#595000
b110010 #
1!
#600000
0!
#605000
b110011 #
1!
#610000
0!
#615000
b110100 #
1!
#620000
0!
#625000
b110101 #
1!
#630000
0!
#635000
b110110 #
1!
#640000
0!
#645000
b110111 #
1!
#650000
0!
#655000
b111000 #
1!
#660000
0!
#665000
b111001 #
1!
#670000
0!
#675000
b111010 #
1!
#680000
0!
#685000
b111011 #
1!
#690000
0!
#695000
b111100 #
1!
#700000
0!
#705000
b111101 #
1!
#710000
0!
#715000
b111110 #
1!
#720000
0!
#725000
b111111 #
1!
#730000
0!
#735000
b1000000 #
1!
#740000
0!
#745000
b1000001 #
1!
#750000
0!
#755000
b1000010 #
1!
#760000
0!
#765000
b1000011 #
1!
#770000
0!
#775000
b1000100 #
1!
#780000
0!
#785000
b1000101 #
1!
#790000
0!
#795000
b1000110 #
1!
#800000
0!
#805000
b1000111 #
1!
#810000
0!
#815000
b1001000 #
1!
#820000
0!
#825000
b1001001 #
1!
#830000
0!
#835000
b1001010 #
1!
#840000
0!
#845000
b1001011 #
1!
#850000
0!
#855000
b1001100 #
1!
#860000
0!
#865000
b1001101 #
1!
#870000
0!
#875000
b1001110 #
1!
#880000
0!
#885000
b1001111 #
1!
#890000
0!
#895000
b1010000 #
1!
#900000
0!
#905000
b1010001 #
1!
#910000
0!
#915000
b1010010 #
1!
#920000
0!
#925000
b1010011 #
1!
#930000
0!
#935000
b1010100 #
1!
#940000
0!
#945000
b1010101 #
1!
#950000
0!
#955000
b1010110 #
1!
#960000
0!
#965000
b1010111 #
1!
#970000
0!
#975000
b1011000 #
1!
#980000
0!
#985000
b1011001 #
1!
#990000
0!
#995000
b1011010 #
1!
